LICENSE.txt
MANIFEST.in
NOTICE.txt
README.rst
requirements.txt
setup.cfg
setup.py
test_requirements.txt
bin/shrew
shrew/__init__.py
shrew/cli.py
shrew.egg-info/PKG-INFO
shrew.egg-info/SOURCES.txt
shrew.egg-info/dependency_links.txt
shrew.egg-info/not-zip-safe
shrew.egg-info/requires.txt
shrew.egg-info/top_level.txt
shrew/utils/__init__.py
shrew/utils/auth.py
shrew/utils/config.py
shrew/utils/file.py
test/test_config.py
test/test_shrew.py