Metadata-Version: 1.0
Name: shrew
Version: 0.1.0a1
Summary: A handy way to manage your bash environment across machines.
Home-page: http://github.com/litters/shrew/
Author: Alan D. Cabrera
Author-email: adc@toolazydogs.com
License: Apache Software License (http://www.apache.org/licenses/LICENSE-2.0)
Platform: any
Classifier: Development Status :: 3 - Alpha
Classifier: Intended Audience :: Developers
Classifier: License :: OSI Approved :: Apache Software License
Classifier: Operating System :: OS Independent
Classifier: Programming Language :: Python
Classifier: Programming Language :: Python :: 2.6
Classifier: Programming Language :: Python :: 2.7
Classifier: Topic :: Software Development :: Libraries :: Python Modules
